LICENCE.txt
MANIFEST.in
README.rst
setup.py
examples/typical_script.py
pompei/__init__.py
pompei/__main__.py
pompei/pompei.py
pompei/version.py
pompei.egg-info/PKG-INFO
pompei.egg-info/SOURCES.txt
pompei.egg-info/dependency_links.txt
pompei.egg-info/requires.txt
pompei.egg-info/top_level.txt