Metadata-Version: 1.0
Name: pompei
Version: 0.1.04
Summary: Create Mosaics from movie frames
Home-page: UNKNOWN
Author: Zulko
Author-email: UNKNOWN
License: see LICENSE.txt
Keywords: mosaic movie frame moviepy
Platform: UNKNOWN
